{
  "parent": "dramaticdoors:recipes/root",
  "rewards": {
    "recipes": [
      "dramaticdoors:tall_aether_skyroot_door"
    ]
  },
  "criteria": {
    "has_the_recipe": {
      "trigger": "minecraft:recipe_unlocked",
      "conditions": {
        "recipe": "dramaticdoors:tall_aether_skyroot_door"
      }
    },
    "has_items": {
      "trigger": "minecraft:inventory_changed",
      "conditions": {
        "items": [
          {
            "items": [ "aether:skyroot_door" ]
          }
        ]
      }
    }
  },
  "requirements": [
    [
      "has_the_recipe",
      "has_items"
    ]
  ],
  "conditions": [
    {
      "type": "forge:mod_loaded",
      "modid": "aether"
    }
  ]
}